{
    "logs": {
        "LogRegisteredTransfer(address,address,uint256,uint256)": 18007,
        "Transfer(address,address,uint256)": 17647,
        "Approval(address,address,uint256)": 4119,
        "OfferTaken(uint256)": 3,
        "TokensReleased(address,uint256)": 3,
        "OwnershipTransferred(address,address)": 2,
        "Upgraded(address)": 2,
        "OfferCreated(uint256)": 1
    },
    "traces": {
        "transfer(address,uint256)": 344,
        "isValid(bytes32)": 226,
        "nativeTransfer": 202,
        "balanceOf(address)": 100,
        "transferFrom(address,address,uint256)": 53,
        "transferERC20(address,address,uint256,uint256)": 45,
        "onTransfer(address,address,uint256)": 26,
        "null": 6,
        "decimals()": 4,
        "approve(address,uint256)": 4,
        "onApprove(address,address,uint256)": 2
    },
    "transactions": {
        "transfer(address,uint256)": 246,
        "transferERC20(address,address,uint256,uint256)": 45,
        "approve(address,uint256)": 3,
        "transferFrom(address,address,uint256)": 2,
        "nativeTransfer": 1
    }
}