{
    "logs": {
        "Transfer(address,address,uint256)": 232676,
        "ReserveAuctionCreated(address,address,uint256,uint256,uint256,uint256,uint256)": 99044,
        "ApprovalForAll(address,address,bool)": 88596,
        "Approval(address,address,uint256)": 85717,
        "BuyPriceSet(address,uint256,address,uint256)": 76405,
        "Minted(address,uint256,string,string)": 72533,
        "ReserveAuctionBidPlaced(uint256,address,uint256,uint256)": 62290,
        "MintFromFixedPriceDrop(address,address,uint256,uint256,uint256,uint256)": 55412,
        "ReserveAuctionFinalized(uint256,address,address,uint256,uint256,uint256)": 31507,
        "ReserveAuctionUpdated(uint256,uint256)": 27727,
        "ReserveAuctionCanceled(uint256)": 23234,
        "NFTCollectionCreated(address,address,uint256,string,string,uint256)": 22176,
        "Initialized(uint8)": 21869,
        "BuyPriceCanceled(address,uint256)": 15706,
        "SellerReferralPaid(address,uint256,address,uint256)": 13154,
        "BalanceLocked(address,uint256,uint256,uint256)": 12642,
        "OfferMade(address,uint256,address,uint256,uint256)": 12642,
        "ETHWithdrawn(address,address,uint256)": 11574,
        "BuyPriceAccepted(address,uint256,address,address,uint256,uint256,uint256)": 10454,
        "NftAddedToExhibition(address,uint256,uint256)": 9074,
        "BalanceUnlocked(address,uint256,uint256)": 7933,
        "OfferAccepted(address,uint256,address,address,uint256,uint256,uint256)": 6255,
        "CreateFixedPriceSale(address,address,uint256,uint256,uint256,uint256,bytes32,string)": 5594,
        "TokenCreatorPaymentAddressSet(address,address,uint256)": 4965,
        "ReserveAuctionInvalidated(uint256)": 4259,
        "RoleGranted(bytes32,address,address)": 4147,
        "BuyPriceInvalidated(address,uint256)": 3560,
        "NFTDropCollectionCreated(address,address,address,string,string,string,bool,uint256,address,uint256,uint256)": 3494,
        "SellersAddedToExhibition(uint256,address[])": 2220,
        "NFTTimedEditionCollectionCreated(address,address,address,string,string,string,uint256,address,uint256,uint256)": 2165,
        "URIUpdated(string,bool)": 1608,
        "CollectionAddedToExhibition(address,uint256)": 1136,
        "NftRemovedFromExhibition(address,uint256,uint256)": 1122,
        "null": 1029,
        "BatchMetadataUpdate(uint256,uint256)": 805,
        "BuyReferralPaid(address,uint256,address,uint256,uint256)": 728,
        "ExhibitionCreated(uint256,address,string,uint16)": 665,
        "OfferInvalidated(address,uint256)": 565,
        "MintFromDutchAuction(address,address,uint256,uint256,uint256)": 305,
        "RebateBuyerFromDutchAuction(address,address,uint256,uint256)": 131,
        "SelfDestruct(address)": 125,
        "TokenCreatorUpdated(address,address,uint256)": 98,
        "ETHTransferred(address,uint256)": 97,
        "ExhibitionDeleted(uint256)": 94,
        "SetSaleStartsAt(address,uint256,address,uint256)": 89,
        "CreateLinearDutchAuction(address,address,uint256,uint256,uint256,uint256,uint256)": 85,
        "MaxTokenIdUpdated(uint256)": 48,
        "WithdrawalToFETH(address,uint256)": 35,
        "Upgraded(address)": 34,
        "MintFromDutchAuctionV2(address,address,uint256,uint256,uint256,uint256,uint256)": 34,
        "WithdrawCreatorRevenueFromDutchAuction(address,uint256,uint256,uint256,uint256)": 28,
        "NFTLimitedEditionCollectionCreated(address,address,address,string,string,string,uint256,address,uint256,uint256)": 26,
        "FundsWithdrawn(address,uint256)": 22,
        "PercentSplitShare(address,uint256)": 18,
        "PercentSplitCreated(address)": 13,
        "BaseURIUpdated(string)": 6,
        "SafeReceived(address,uint256)": 5,
        "MinterAcquireSupplyLock(address,uint256)": 4,
        "AdminChanged(address,address)": 3,
        "CollectionTemplateUpdated(uint8,address,uint256)": 3,
        "AddMerkleRootToFixedPriceSale(address,bytes32,string)": 3,
        "NFTMarketUpdated(address)": 1,
        "ProxyCallContractUpdated(address)": 1
    },
    "traces": {
        "null": 28823,
        "nativeTransfer": 3021,
        "getBuyPrice(address,uint256)": 2490,
        "getReserveAuctionIdFor(address,uint256)": 2490,
        "upsertListingV2(address,uint256,uint256,uint256,uint256,bool,uint256,uint256)": 2442,
        "transferFrom(address,address,uint256)": 2208,
        "getSaleStartsAt(address,uint256)": 2124,
        "supportsInterface(bytes4)": 1838,
        "mintCountTo(uint16,address)": 1540,
        "mintFromFixedPriceSaleWithEarlyAccessAllowlist(address,uint256,address,bytes32[])": 1398,
        "royaltyInfo(uint256,uint256)": 1234,
        "tokenCreator(uint256)": 1234,
        "createReserveAuctionV3(address,uint256,uint256,uint256,uint256)": 1186,
        "setBuyPriceV2(address,uint256,uint256,uint256)": 1006,
        "getNFTCollectionType()": 1006,
        "mintAndApprove(string,address)": 958,
        "getReserveAuction(uint256)": 722,
        "getTransactionBreakdown((uint256,bool,address,uint256,uint256,address,address,uint16,address))": 705,
        "getExhibitionPaymentDetails(uint256)": 694,
        "placeBidV2(uint256,uint256,address)": 500,
        "setApprovalForAll(address,bool)": 376,
        "finalizeReserveAuction(uint256)": 338,
        "cancelReserveAuction(uint256)": 316,
        "hasRole(bytes32,address)": 302,
        "updateReserveAuctionV2(uint256,uint256,uint256)": 302,
        "createNFTCollection(string,string,uint96)": 282,
        "setSaleStartsAt(address,uint256,uint256)": 272,
        "mintWithCreatorPaymentFactoryAndApprove(string,address,bytes,address)": 260,
        "initialize(address,string,string)": 205,
        "cancelBuyPrice(address,uint256)": 196,
        "createFixedPriceSaleV3(address,uint256,uint256,uint256,uint256,uint256)": 176,
        "burn(uint256)": 156,
        "numberOfTokensAvailableToMint()": 151,
        "createSplit((address,uint256)[])": 138,
        "safeTransferFrom(address,address,uint256,bytes)": 134,
        "buyV2(address,uint256,uint256,address)": 100,
        "selfDestruct()": 96,
        "createNFTLimitedEditionCollection(string,string,string,uint32,address,uint96)": 88,
        "createLimitedEditionCollectionAndFixedPriceSale((string,string,string,uint32,uint96),(uint256,uint256,uint256,uint256),uint256)": 88,
        "mintFromDutchAuction(address,uint256)": 86,
        "makeOfferV2(address,uint256,uint256,address)": 80,
        "setBuyPrice(address,uint256,uint256)": 78,
        "marketLockupFor(address,uint256)": 76,
        "safeTransferFrom(address,address,uint256)": 70,
        "addSellersToExhibition(uint256,address[])": 70,
        "mintFromFixedPriceSale(address,uint16,address)": 64,
        "initialize(address,string,string,string,uint32,address,address)": 62,
        "batchListFromCollectionV2(address,uint256[],uint256,uint256,uint256,bool,uint256)": 62,
        "createNFTDropCollection(string,string,string,bool,uint32,address,uint96)": 52,
        "createNFTTimedEditionCollection(string,string,string,uint256,address,uint96)": 48,
        "createTimedEditionCollectionAndFixedPriceSaleV2((string,string,string,uint96),(uint256,uint256,uint256,uint256,uint256),uint256)": 48,
        "initialize((address,uint256)[])": 44,
        "isAllowedSellerForExhibition(uint256,address)": 42,
        "getExhibitionIdForNft(address,uint256)": 40,
        "initialize(address,string,string,string,bool,uint32,address,address)": 37,
        "acceptOffer(address,uint256,address,uint256)": 36,
        "marketWithdrawLocked(address,uint256,uint256)": 36,
        "initialize(address,string,string,string,uint256,address,address)": 36,
        "reveal(string)": 34,
        "rebateBuyerFromDutchAuction(address,address)": 34,
        "ownerOf(uint256)": 29,
        "createExhibition(string,uint16,address[])": 24,
        "updateExhibitionNft(address,uint256,uint256)": 22,
        "marketWithdrawFrom(address,uint256)": 20,
        "createLinearDutchAuction(address,uint256,uint256,uint256,uint256,uint256,uint256)": 18,
        "minterAcquireSupplyLock(uint256)": 16,
        "withdrawAvailableBalance()": 10,
        "createTimedEditionCollectionAndFixedPriceSaleWithPaymentFactoryV2((string,string,string,uint96),(address,bytes),(uint256,uint256,uint256,uint256,uint256),uint256)": 8,
        "createNFTTimedEditionCollectionWithPaymentFactory(string,string,string,uint256,address,uint96,(address,bytes))": 8,
        "deleteExhibition(uint256)": 6,
        "approve(address,uint256)": 4,
        "tokenURI(uint256)": 4,
        "marketChangeLockup(address,uint256,uint256,address,uint256)": 4,
        "onERC721Received(address,address,uint256,bytes)": 2
    },
    "transactions": {
        "createNFTCollection(string,string,uint96)": 22356,
        "createNFTDropCollection(string,string,string,bool,uint32,address,uint96)": 3344,
        "upsertListingV2(address,uint256,uint256,uint256,uint256,bool,uint256,uint256)": 1221,
        "mintFromFixedPriceSaleWithEarlyAccessAllowlist(address,uint256,address,bytes32[])": 702,
        "mintAndApprove(string,address)": 481,
        "placeBidV2(uint256,uint256,address)": 250,
        "setApprovalForAll(address,bool)": 186,
        "createNFTDropCollectionWithPaymentFactory(string,string,string,bool,uint32,address,uint96,(address,bytes))": 181,
        "finalizeReserveAuction(uint256)": 169,
        "mintWithCreatorPaymentFactoryAndApprove(string,address,bytes,address)": 130,
        "burn(uint256)": 78,
        "nativeTransfer": 73,
        "safeTransferFrom(address,address,uint256,bytes)": 59,
        "buyV2(address,uint256,uint256,address)": 50,
        "selfDestruct()": 48,
        "mintFromDutchAuction(address,uint256)": 44,
        "createLimitedEditionCollectionAndFixedPriceSale((string,string,string,uint32,uint96),(uint256,uint256,uint256,uint256),uint256)": 44,
        "makeOfferV2(address,uint256,uint256,address)": 40,
        "addSellersToExhibition(uint256,address[])": 35,
        "mintFromFixedPriceSale(address,uint16,address)": 32,
        "batchListFromCollectionV2(address,uint256[],uint256,uint256,uint256,bool,uint256)": 31,
        "safeTransferFrom(address,address,uint256)": 26,
        "createTimedEditionCollectionAndFixedPriceSaleV2((string,string,string,uint96),(uint256,uint256,uint256,uint256,uint256),uint256)": 24,
        "acceptOffer(address,uint256,address,uint256)": 18,
        "reveal(string)": 17,
        "rebateBuyerFromDutchAuction(address,address)": 17,
        "createFixedPriceSaleV3(address,uint256,uint256,uint256,uint256,uint256)": 16,
        "createExhibition(string,uint16,address[])": 12,
        "createLinearDutchAuction(address,uint256,uint256,uint256,uint256,uint256,uint256)": 9,
        "transferFrom(address,address,uint256)": 9,
        "withdrawAvailableBalance()": 5,
        "createTimedEditionCollectionAndFixedPriceSaleWithPaymentFactoryV2((string,string,string,uint96),(address,bytes),(uint256,uint256,uint256,uint256,uint256),uint256)": 4,
        "deleteExhibition(uint256)": 3,
        "approve(address,uint256)": 2,
        "selfDestructMigration()": 1
    }
}