{
    "logs": {
        "null": 23707,
        "MetadataUpdated(uint256,(uint256,string))": 2474,
        "ProjectCreated(uint256,address)": 1166,
        "ProgramCreated(address,address)": 76,
        "Initialized(uint8)": 54,
        "VotingContractCreated(address,address)": 47,
        "PayoutContractCreated(address,address)": 45,
        "Upgraded(address)": 14,
        "OwnershipTransferred(address,address)": 12,
        "AdminChanged(address,address)": 8,
        "PayoutImplementationUpdated(address)": 3,
        "VotingContractUpdated(address)": 3,
        "RoundImplementationUpdated(address)": 3,
        "AlloSettingsUpdated(address)": 1,
        "ProgramContractUpdated(address)": 1
    },
    "traces": {
        "null": 68
    },
    "transactions": {
        "create()": 37,
        "nativeTransfer": 4,
        "updateVotingContract(address)": 3
    }
}