{
    "logs": {
        "Sync(uint256,uint256)": 50639,
        "Transfer(address,address,uint256)": 45719,
        "Fees(address,uint256,uint256)": 44308,
        "Swap(address,uint256,uint256,uint256,uint256,address)": 44308,
        "Approval(address,address,uint256)": 11535,
        "Mint(address,uint256,uint256)": 4465,
        "Supply(uint256,uint256)": 2786,
        "Voted(address,uint256,address,int256)": 2785,
        "Deposit(address,uint256,uint256,uint256,uint8,uint256)": 2742,
        "Burn(address,uint256,uint256,address)": 2731,
        "Deposit(address,address,uint256,uint256)": 1169,
        "Claimed(uint256,uint256,uint256,uint256)": 804,
        "Withdraw(address,address,uint256,uint256)": 584,
        "Claim(address,address,uint256,uint256)": 490,
        "Attach(address,address,uint256)": 411,
        "Detach(address,address,uint256)": 374,
        "Abstained(uint256,address,int256)": 303,
        "ApprovalForAll(address,address,bool)": 86,
        "null": 81,
        "DistributeReward(address,address,uint256)": 73,
        "Whitelisted(address,address)": 53,
        "GaugeCreated(address,address,address,address)": 44,
        "Withdraw(address,uint256,uint256,uint256)": 44,
        "Blacklisted(address,address)": 37,
        "Mint(address,uint256,uint256,uint256)": 36,
        "NotifyReward(address,address,uint256)": 36,
        "CheckpointToken(uint256,uint256)": 36,
        "Delegate(address,address,uint256)": 3,
        "Withdrawal(address,uint256)": 3
    },
    "traces": {
        "null": 330811,
        "balanceOf(address)": 834,
        "childSubImplementationAddress()": 752,
        "balanceOfNFTAt(uint256,uint256)": 470,
        "transfer(address,uint256)": 427,
        "transferFrom(address,address,uint256)": 305,
        "isDelegateOrOwner(address,uint256)": 228,
        "balanceOfNFT(uint256)": 228,
        "vote(uint256,address[],int256[])": 228,
        "isPaused()": 168,
        "approve(address,uint256)": 132,
        "getAmountOut(uint256,address)": 118,
        "token0()": 80,
        "reserve0()": 70,
        "isPair(address)": 66,
        "swapExactTokensForTokens(uint256,uint256,(address,address,bool)[],address,uint256)": 52,
        "reserve1()": 44,
        "increase_unlock_time(uint256,uint256)": 42,
        "user_point_history(uint256,uint256)": 42,
        "active_period()": 42,
        "distribute(address)": 38,
        "update_period()": 38,
        "user_point_epoch(uint256)": 36,
        "point_history(uint256)": 26,
        "getReserves()": 22,
        "burn(address)": 22,
        "isApprovedOrOwner(address,uint256)": 20,
        "locked__end(uint256)": 20,
        "deposit_for(uint256,uint256)": 20,
        "claim(uint256)": 20,
        "removeLiquidity(address,address,bool,uint256,uint256,uint256,address,uint256)": 18,
        "claimable(uint256)": 16,
        "locked(uint256)": 16,
        "metadata()": 16,
        "detachTokenFromGauge(uint256,address)": 12,
        "stable()": 12,
        "usedWeights(uint256)": 12,
        "totalSupply()": 12,
        "getPair(address,address,bool)": 12,
        "allowance(address,address)": 12,
        "mint(address)": 12,
        "nativeTransfer": 12,
        "detach(uint256)": 12,
        "addLiquidity(address,address,bool,uint256,uint256,uint256,uint256,address,uint256)": 12,
        "ownerOf(uint256)": 10,
        "swapExactTokensForETH(uint256,uint256,(address,address,bool)[],address,uint256)": 8,
        "safeTransferFrom(address,address,uint256,bytes)": 8,
        "getApproved(uint256)": 8,
        "swap(uint256,uint256,address,bytes)": 6,
        "swapExactTokensForTokensSimple(uint256,uint256,address,address,bool,address,uint256)": 6,
        "merge(uint256,uint256)": 4,
        "withdraw(uint256)": 4,
        "_token()": 4,
        "isVaultToken()": 2,
        "notifyRewardAmount(uint256)": 2,
        "checkpoint()": 2,
        "attach(uint256)": 2,
        "checkpoint_token()": 2,
        "attachTokenToGauge(uint256,address)": 2,
        "checkpoint_total_supply()": 2,
        "mint(address,uint256)": 2,
        "epoch()": 2
    },
    "transactions": {
        "setPoolSpecificFees(address,uint256,bool)": 142,
        "vote(uint256,address[],int256[])": 110,
        "approve(address,uint256)": 38,
        "increase_unlock_time(uint256,uint256)": 21,
        "claim(uint256)": 10,
        "removeLiquidity(address,address,bool,uint256,uint256,uint256,address,uint256)": 9,
        "distribute(address)": 8,
        "swapExactTokensForTokens(uint256,uint256,(address,address,bool)[],address,uint256)": 6,
        "addLiquidity(address,address,bool,uint256,uint256,uint256,uint256,address,uint256)": 5,
        "transfer(address,uint256)": 4,
        "safeTransferFrom(address,address,uint256,bytes)": 4,
        "swapExactTokensForETH(uint256,uint256,(address,address,bool)[],address,uint256)": 4,
        "merge(uint256,uint256)": 2,
        "setOwner2Address(address)": 2,
        "createPair(address,address,bool)": 1,
        "updateGovernanceAddressAll(address)": 1,
        "deploy(bytes,uint256)": 1,
        "setOwner1Address(address)": 1
    }
}